wikibot/__init__.py
wikibot/wikibot.py
my_wiki_bot-0.0.2.dist-info/LICENSE
my_wiki_bot-0.0.2.dist-info/METADATA
my_wiki_bot-0.0.2.dist-info/WHEEL
my_wiki_bot-0.0.2.dist-info/top_level.txt
my_wiki_bot-0.0.2.dist-info/RECORD
