Metadata-Version: 2.1
Name: my-wiki-bot
Version: 0.0.2
Summary: A simple wrapper of atlassian-python-api for complex confluence page content modification.
Home-page: https://github.com/jnhyperion/WikiBot
Author: Johnny Huang
Author-email: jnhyperion@gmail.com
License: UNKNOWN
Keywords: atlassian confluence modification
Platform: UNKNOWN
Classifier: Programming Language :: Python :: 3
Classifier: License :: OSI Approved :: MIT License
Classifier: Operating System :: OS Independent
Requires-Python: >=3.6
Requires-Dist: atlassian-python-api
Requires-Dist: beautifulsoup4
